xfilepy/__init__.py
xfilepy/_base.py
xfilepy/_platform.py
xfilepy/android.py
xfilepy/desktop.py
xfilepy/ios.py
xfilepy-0.2.1.dist-info/WHEEL
xfilepy-0.2.1.dist-info/METADATA
xfilepy-0.2.1.dist-info/RECORD
