Metadata-Version: 2.4
Name: xfilepy
Version: 0.2.1
Summary: Cross-platform, file handler using native pickers and security models.
Keywords: kivy,android,ios,desktop,files,document picker
Author: Moritz R. Schäfer
Author-email: Moritz R. Schäfer <moritz.schaefer-f91@rub.de>
License-Expression: GPL-3.0-or-later
Requires-Dist: crossfiledialog>=1.1.0
Requires-Dist: kivy ; extra == 'android'
Requires-Dist: pyjnius ; extra == 'android'
Requires-Dist: pdoc ; extra == 'docs'
Requires-Dist: kivy ; extra == 'ios'
Requires-Dist: pyobjus ; extra == 'ios'
Maintainer: Moritz R. Schäfer
Maintainer-email: Moritz R. Schäfer <moritz.schaefer-f91@rub.de>
Requires-Python: >=3.11
Project-URL: Repository, https://gitlab.com/M0M097/xfilepy
Project-URL: Documentation, https://xfile-fb4acf.gitlab.io/
Project-URL: Issues, https://gitlab.com/M0M097/xfilepy/-/issues
Provides-Extra: android
Provides-Extra: docs
Provides-Extra: ios
